Workbook
Name aporte: Investimentos!$D$15:$D$15
Name patrimonio: Investimentos!$D$18:$D$18
Name perfil: Investimentos!$C$32:$D$32
Name qtd_meses: Investimentos!$D$16:$D$16
Name rendimento_carteira: Investimentos!$D$11:$D$11
Name salario: Investimentos!$D$10:$D$10
Name sugestao_investimento: Investimentos!$D$12:$D$12
Name taxa_mensal: Investimentos!$D$17:$D$17

Sheet Investimentos
B9: CONFIGURAÇÕES
B10: Salário | D10: 5000
B11: Rendimento Carteira | D11: 0.01
B12: Sugestão de Investimento (30%) | D12: =D10*30% -> 1500
B14: INVESTIMENTO MENSAL
B15: Quanto investir por mês? | D15: 781
B16: Por quantos meses? | D16: 12
B17: Taxa de rendimento mensal? | D17: 0.011715
B18: Patrimônio Acumulado? | D18: {=FV(taxa_mensal,qtd_meses,aporte*-1)} -> 10000.076
B19: Dividendos mensais? | D19: {=patrimonio*rendimento_carteira} -> 100.00076
B22: CENÁRIOS | D22: DIVIDENDOS
A23: 3 | B23: Quanto em 3 anos? | C23: {=FV(taxa_mensal,A23*12,aporte*-1)} -> 34725.3 | D23: {=C23*rendimento_carteira} -> 347.253
A24: 6 | B24: quanto em 6 anos?* | C24: {=FV(taxa_mensal,A24*12,aporte*-1)} -> 87538.296 | D24: {=C24*rendimento_carteira} -> 875.38296
A25: 9 | B25: Quanto em 9 anos?** | C25: {=FV(taxa_mensal,A25*12,aporte*-1)} -> 167860.5 | D25: {=C25*rendimento_carteira} -> 1678.605
A26: 11 | B26: Quanto em 11 anos?*** | C26: {=FV(taxa_mensal,A26*12,aporte*-1)} -> 243496.12 | D26: {=C26*rendimento_carteira} -> 2434.9612
A27: 20 | B27: Quanto em 20 anos? | C27: {=FV(taxa_mensal,A27*12,aporte*-1)} -> 1024457.3 | D27: {=C27*rendimento_carteira} -> 10244.573
B28: *Passa a receber o mesmo valor que investe
B29: *Passa a receber o dobro do que investe
B30: *Passa a receber o triplo do que investe
B32: PERFIL | C32: AGRESSIVO
B33: Valor a ser investido por mês | C33: {=aporte} -> 781
B35: TIPO DE FII | C35: Percentual Sugerido | D35: Valores
B36: PAPEL | C36: =VLOOKUP($C$32&"-"&B36,'Percentual&Perfil'!$B$2:$E$20,4,FALSE) -> 0.4 | D36: {=aporte*C36} -> 312.4
B37: TIJOLO | C37: =VLOOKUP($C$32&"-"&B37,'Percentual&Perfil'!$B$2:$E$20,4,FALSE) -> 0.2 | D37: {=aporte*C37} -> 156.2
B38: HÍBRIDOS | C38: =VLOOKUP($C$32&"-"&B38,'Percentual&Perfil'!$B$2:$E$20,4,FALSE) -> 0.05 | D38: {=aporte*C38} -> 39.05
B39: FOFs | C39: =VLOOKUP($C$32&"-"&B39,'Percentual&Perfil'!$B$2:$E$20,4,FALSE) -> 0.05 | D39: {=aporte*C39} -> 39.05
B40: DESENVOLVIMENTO | C40: =VLOOKUP($C$32&"-"&B40,'Percentual&Perfil'!$B$2:$E$20,4,FALSE) -> 0.15 | D40: {=aporte*C40} -> 117.15
B41: HOTELARIAS | C41: =VLOOKUP($C$32&"-"&B41,'Percentual&Perfil'!$B$2:$E$20,4,FALSE) -> 0.15 | D41: {=aporte*C41} -> 117.15
D42: =SUM(D36:D41) -> 781

Sheet Percentual&Perfil
B2: CHAVE | C2: PERFIL | D2: TIPO DE FII | E2: PERCENTUAL
B3: =C3&"-"&D3 -> CONSERVADOR-PAPEL | C3: CONSERVADOR | D3: PAPEL | E3: 0.3
B4: =C4&"-"&D4 -> CONSERVADOR-TIJOLO | C4: CONSERVADOR | D4: TIJOLO | E4: 0.5
B5: =C5&"-"&D5 -> CONSERVADOR-HÍBRIDOS | C5: CONSERVADOR | D5: HÍBRIDOS | E5: 0.1
B6: =C6&"-"&D6 -> CONSERVADOR-FOFs | C6: CONSERVADOR | D6: FOFs | E6: 0.1
B7: =C7&"-"&D7 -> CONSERVADOR-DESENVOLVIMENTO | C7: CONSERVADOR | D7: DESENVOLVIMENTO | E7: 0
B8: =C8&"-"&D8 -> CONSERVADOR-HOTELARIAS | C8: CONSERVADOR | D8: HOTELARIAS | E8: 0
B9: =C9&"-"&D9 -> MODERADO-PAPEL | C9: MODERADO | D9: PAPEL | E9: 0.3
B10: =C10&"-"&D10 -> MODERADO-TIJOLO | C10: MODERADO | D10: TIJOLO | E10: 0.4
B11: =C11&"-"&D11 -> MODERADO-HÍBRIDOS | C11: MODERADO | D11: HÍBRIDOS | E11: 0.1
B12: =C12&"-"&D12 -> MODERADO-FOFs | C12: MODERADO | D12: FOFs | E12: 0.1
B13: =C13&"-"&D13 -> MODERADO-DESENVOLVIMENTO | C13: MODERADO | D13: DESENVOLVIMENTO | E13: 0.05
B14: =C14&"-"&D14 -> MODERADO-HOTELARIAS | C14: MODERADO | D14: HOTELARIAS | E14: 0.05
... B20: =C20&"-"&D20 -> AGRESSIVO-HOTELARIAS | C20: AGRESSIVO | D20: HOTELARIAS | E20: 0.15
